requirements.txt
loomchild/__init__.py
loomchild/segmenter.py
loomchild/data/segment-2.0.4-SNAPSHOT/lib/commons-cli-1.2.jar
loomchild/data/segment-2.0.4-SNAPSHOT/lib/commons-logging-1.2.jar
loomchild/data/segment-2.0.4-SNAPSHOT/lib/gson-2.8.0.jar
loomchild/data/segment-2.0.4-SNAPSHOT/lib/hamcrest-core-1.3.jar
loomchild/data/segment-2.0.4-SNAPSHOT/lib/jakarta.activation-1.2.2.jar
loomchild/data/segment-2.0.4-SNAPSHOT/lib/jakarta.xml.bind-api-2.3.3.jar
loomchild/data/segment-2.0.4-SNAPSHOT/lib/javax.activation-api-1.2.0.jar
loomchild/data/segment-2.0.4-SNAPSHOT/lib/jaxb-api-2.3.1.jar
loomchild/data/segment-2.0.4-SNAPSHOT/lib/jaxb-core-2.3.0.1.jar
loomchild/data/segment-2.0.4-SNAPSHOT/lib/jaxb-impl-2.3.3.jar
loomchild/data/segment-2.0.4-SNAPSHOT/lib/junit-4.13.1.jar
loomchild/data/segment-2.0.4-SNAPSHOT/lib/segment-2.0.4-SNAPSHOT-tests.jar
loomchild/data/segment-2.0.4-SNAPSHOT/lib/segment-2.0.4-SNAPSHOT.jar
loomchild/data/segment-2.0.4-SNAPSHOT/lib/segment-ui-2.0.4-SNAPSHOT.jar
loomchild/data/srx/Aggressive.srx
loomchild/data/srx/NonAggressive.srx
loomchild/data/srx/OmegaT.srx
loomchild/data/srx/PTDR.srx
loomchild/data/srx/language_tools.segment.srx
loomchild_segment-2.0.4.2.data/scripts/py-segment
loomchild_segment-2.0.4.2.dist-info/LICENSE
loomchild_segment-2.0.4.2.dist-info/METADATA
loomchild_segment-2.0.4.2.dist-info/WHEEL
loomchild_segment-2.0.4.2.dist-info/top_level.txt
loomchild_segment-2.0.4.2.dist-info/RECORD
