Metadata-Version: 2.1
Name: loomchild-segment
Version: 2.0.4.2
Summary: Python wrapper for Loomchild segmenter
Home-page: https://github.com/bitextor/loomchild-segment-py
Author: Prompsit Language Engineering
Author-email: info@prompsit.com
Maintainer: Marta Bañon, Elsa Sarrías
Maintainer-email: mbanon@prompsit.com, esarrias@dlsi.ua.es
License: GNU General Public License v3.0
Project-URL: loomchild-segment-py on GitHub, https://github.com/bitextor/loomchild-segment-py
Project-URL: Loomchild segment on GitHub, https://github.com/mbanon/segment
Project-URL: Bifixer on GitHub, https://github.com/bitextor/bifixer
Project-URL: Prompsit Language Engineering, http://www.prompsit.com
Project-URL: Paracrawl, https://paracrawl.eu/
Classifier: Environment :: Console
Classifier: Intended Audience :: Science/Research
Classifier: Programming Language :: Python :: 3.7
Classifier: License :: OSI Approved :: GNU General Public License v3 (GPLv3)
Classifier: Operating System :: POSIX :: Linux
Classifier: Topic :: Text Processing :: Linguistic
Classifier: Topic :: Software Development :: Libraries :: Python Modules
License-File: LICENSE
Requires-Dist: toolwrapper (>=0.4.1)
